pycitydata/__init__.py
pycitydata/map/__init__.py
pycitydata/map/format_converter.py
pycitydata/map/map.py
pycitydata/sateimg/__init__.py
pycitydata/sateimg/_utils.py
pycitydata/sateimg/sateimg.py
pycitydata/streetview/__init__.py
pycitydata/streetview/baidu.py
pycitydata/streetview/equirectangular.py
pycitydata/streetview/google.py
pycitydata/urbankg/__init__.py
pycitydata/urbankg/kg.py
pycitydata-2.0.0.dist-info/LICENSE
pycitydata-2.0.0.dist-info/METADATA
pycitydata-2.0.0.dist-info/WHEEL
pycitydata-2.0.0.dist-info/RECORD
