Metadata-Version: 2.3
Name: pycitydata
Version: 2.0.0
Summary: City Data Python SDK
License: MIT
Author: Jun Zhang
Author-email: zhangjun990222@qq.com
Requires-Python: >=3.9
Classifier: License :: OSI Approved :: MIT License
Classifier: Operating System :: OS Independent
Classifier: Programming Language :: Python :: 3
Classifier: Programming Language :: Python :: 3.9
Classifier: Programming Language :: Python :: 3.10
Classifier: Programming Language :: Python :: 3.11
Classifier: Programming Language :: Python :: 3.12
Classifier: Programming Language :: Python :: 3.13
Requires-Dist: geojson (>=3.1.0)
Requires-Dist: geopandas (>=0.9.0)
Requires-Dist: lru-dict (>=1.3.0)
Requires-Dist: numpy (>=1.24.0)
Requires-Dist: opencv-python-headless (>=4.8.0.0)
Requires-Dist: pillow (>=10.0.0)
Requires-Dist: pycityproto (>=2.3.5,<3.0.0)
Requires-Dist: pymongo (>=3.12.1)
Requires-Dist: pyproj (>=3.0.0)
Requires-Dist: requests (>=2.27.0)
Requires-Dist: scipy (>=1.7.0)
Requires-Dist: shapely (>=2.0.0)
Requires-Dist: stringcase (>=1.2.0,<2.0.0)
Project-URL: Documentation, https://docs.fiblab.net/pycitydata
Project-URL: Homepage, https://github.com/tsinghua-fib-lab/pycitydata
Project-URL: Repository, https://github.com/tsinghua-fib-lab/pycitydata
